<?xml version="1.0" encoding="UTF-8"?><factura id="comprobante" version="1.1.0"><infoTributaria><ambiente>1</ambiente><tipoEmision>1</tipoEmision><razonSocial>MANOBANDA YUGCHA JOSE FRANCISCO</razonSocial><ruc>1891809449001</ruc><claveAcceso>1910202501189180944900110012000000025692844292411</claveAcceso><codDoc>01</codDoc><estab>001</estab><ptoEmi>200</ptoEmi><secuencial>000002569</secuencial><dirMatriz>Ambato</dirMatriz></infoTributaria><infoFactura><fechaEmision>19/10/2025</fechaEmision><dirEstablecimiento>Ambato</dirEstablecimiento><obligadoContabilidad>NO</obligadoContabilidad><tipoIdentificacionComprador>04</tipoIdentificacionComprador><guiaRemision>001-300-000002569</guiaRemision><razonSocialComprador>TITE HARO RAMIRO MATIAS</razonSocialComprador><identificacionComprador>1850137918001</identificacionComprador><direccionComprador>Avenida UTA</direccionComprador><totalSinImpuestos>100.5</totalSinImpuestos><totalDescuento>0</totalDescuento><totalConImpuestos><totalImpuesto><codigo>2</codigo><codigoPorcentaje>0</codigoPorcentaje><descuentoAdicional>0.00</descuentoAdicional><baseImponible>100.5</baseImponible><valor>0</valor></totalImpuesto></totalConImpuestos><importeTotal>100.5</importeTotal><moneda>dolar</moneda><pagos><pago><formaPago>01</formaPago><total>100.5</total></pago></pagos></infoFactura><detalles><detalle><codigoPrincipal>EXC001</codigoPrincipal><codigoAuxiliar>OTR001</codigoAuxiliar><descripcion>Tarifa Básica Diciembre</descripcion><cantidad>1</cantidad><precioUnitario>100.5</precioUnitario><descuento>0</descuento><precioTotalSinImpuesto>100.5</precioTotalSinImpuesto><impuestos><impuesto><codigo>2</codigo><codigoPorcentaje>0</codigoPorcentaje><tarifa>0.00</tarifa><baseImponible>100.5</baseImponible><valor>0</valor></impuesto></impuestos></detalle></detalles><infoAdicional><campoAdicional nombre="emailcliente">henrystevencortez@gmail.com</campoAdicional></infoAdicional></factura>